aesthetix/__init__.py
aesthetix-0.0.1.dist-info/LICENSE
aesthetix-0.0.1.dist-info/METADATA
aesthetix-0.0.1.dist-info/WHEEL
aesthetix-0.0.1.dist-info/top_level.txt
aesthetix-0.0.1.dist-info/RECORD
