Metadata-Version: 2.1
Name: aesthetix
Version: 0.0.1
Summary: A small package for aesthetic output in custom machine learning pipelines
Home-page: UNKNOWN
Author: Abhay Dayal Mathur
Author-email: admathur@iitk.ac.in
License: UNKNOWN
Platform: UNKNOWN
Classifier: Programming Language :: Python :: 3
Classifier: License :: OSI Approved :: MIT License
Classifier: Operating System :: OS Independent
Requires-Python: >=3.6
